odoo9_addon_l10n_cn_partner-9.0.1.0.2.99.dev2-py2.7-nspkg.pth
odoo9_addon_l10n_cn_partner-9.0.1.0.2.99.dev2.dist-info/METADATA
odoo9_addon_l10n_cn_partner-9.0.1.0.2.99.dev2.dist-info/RECORD
odoo9_addon_l10n_cn_partner-9.0.1.0.2.99.dev2.dist-info/WHEEL
odoo9_addon_l10n_cn_partner-9.0.1.0.2.99.dev2.dist-info/namespace_packages.txt
odoo9_addon_l10n_cn_partner-9.0.1.0.2.99.dev2.dist-info/top_level.txt
odoo_addons/l10n_cn_partner/README.rst
odoo_addons/l10n_cn_partner/__init__.py
odoo_addons/l10n_cn_partner/__openerp__.py
odoo_addons/l10n_cn_partner/i18n/zh_CN.po
odoo_addons/l10n_cn_partner/models/__init__.py
odoo_addons/l10n_cn_partner/models/partner.py
odoo_addons/l10n_cn_partner/static/description/icon.png
odoo_addons/l10n_cn_partner/views/partner_view.xml
