Metadata-Version: 2.1
Name: odoo9-addon-l10n-cn-partner
Version: 9.0.1.0.2.99.dev2
Summary: l10n_hr
Home-page: https://www.elico-corp.com/
Author: Elico corp
Author-email: UNKNOWN
License: AGPL-3
Platform: UNKNOWN
Classifier: Programming Language :: Python
Classifier: Framework :: Odoo
Classifier: License :: OSI Approved :: GNU Affero General Public License v3
Requires-Python: ~=2.7
Requires-Dist: odoo (<9.1a,>=9.0a)
